yasem/__init__.py
yasem/splade_embedder.py
yasem-0.4.1.dist-info/LICENSE.txt
yasem-0.4.1.dist-info/METADATA
yasem-0.4.1.dist-info/WHEEL
yasem-0.4.1.dist-info/top_level.txt
yasem-0.4.1.dist-info/RECORD
