Metadata-Version: 2.1
Name: yasem
Version: 0.4.1
Summary: YASEM - Yet Another Splade|Sparse Embedder - A simple and efficient library for SPLADE embeddings
Author-email: Yuichi Tateno <hotchpotch@gmail.com>
License: MIT
Project-URL: homepage, https://github.com/hotchpotch/yasem
Project-URL: repository, https://github.com/hotchpotch/yasem
Keywords: nlp,embeddings,splade,sparse-vectors
Requires-Python: >=3.9
License-File: LICENSE.txt
Requires-Dist: numpy>=2.0.0
Requires-Dist: scipy>=1.13.1
Requires-Dist: torch>=2.2.0
Requires-Dist: transformers>=4.44.0
